python_ssdb-1.0.5.dist-info/LICENSE
python_ssdb-1.0.5.dist-info/WHEEL
python_ssdb-1.0.5.dist-info/top_level.txt
python_ssdb-1.0.5.dist-info/RECORD
python_ssdb-1.0.5.dist-info/METADATA
python_ssdb-1.0.5.dist-info/NOTICE.md
ssdb/__init__.py
ssdb/client.cpython-39-i386-linux-gnu.so
ssdb/connection.cpython-39-i386-linux-gnu.so
ssdb/core/interface.cpython-39-i386-linux-gnu.so
ssdb/core/encode.cpython-39-i386-linux-gnu.so
ssdb/core/__init__.py
ssdb/core/response.cpython-39-i386-linux-gnu.so
ssdb/core/parser.cpython-39-i386-linux-gnu.so
ssdb/asyncio/__init__.py
ssdb/asyncio/client.cpython-39-i386-linux-gnu.so
ssdb/asyncio/connection.cpython-39-i386-linux-gnu.so
