Metadata-Version: 2.1
Name: python-ssdb
Version: 1.0.5
Summary: SSDB Python Client
Home-page: https://github.com/kakao/python-ssdb
Author: recoteam
Author-email: recoteam@kakaocorp.com
License: Apache2
Keywords: SSDB
Classifier: License :: OSI Approved :: Apache Software License
Classifier: Operating System :: POSIX :: Linux
Classifier: Operating System :: MacOS :: MacOS X
Classifier: Operating System :: Microsoft :: Windows
Classifier: Programming Language :: Python :: 3.9
Classifier: Programming Language :: Python :: 3.10
Classifier: Programming Language :: Python :: 3.11
Classifier: Programming Language :: Cython
Requires-Python: >=3.9
License-File: LICENSE
License-File: NOTICE.md
